JaxVidFlow/__init__.py
JaxVidFlow/colourspaces.py
JaxVidFlow/compat.py
JaxVidFlow/config.py
JaxVidFlow/gyroflow.py
JaxVidFlow/lut.py
JaxVidFlow/nlmeans.py
JaxVidFlow/normalize.py
JaxVidFlow/scale.py
JaxVidFlow/types.py
JaxVidFlow/utils.py
JaxVidFlow/video_reader.py
JaxVidFlow/video_writer.py
jaxvidflow-0.0.8.dist-info/METADATA
jaxvidflow-0.0.8.dist-info/WHEEL
jaxvidflow-0.0.8.dist-info/licenses/LICENSE
jaxvidflow-0.0.8.dist-info/RECORD
