Metadata-Version: 2.4
Name: JaxVidFlow
Version: 0.0.8
Summary: Video processing library using JAX.
Project-URL: Homepage, https://github.com/matthewlai/JaxVidFlow
Project-URL: Issues, https://github.com/matthewlai/JaxVidFlow/issues
Author-email: Matthew Lai <m@matthewlai.ca>
License-File: LICENSE
Classifier: License :: OSI Approved :: GNU Lesser General Public License v3 or later (LGPLv3+)
Classifier: Operating System :: MacOS
Classifier: Operating System :: Microsoft :: Windows
Classifier: Operating System :: POSIX :: Linux
Classifier: Programming Language :: Python :: 3
Requires-Python: >=3.11
Requires-Dist: av>=14.1.0
Requires-Dist: jax
Requires-Dist: numpy
Requires-Dist: scipy
Requires-Dist: tqdm
